{
  "musician": "안치환",
  "title": "내가 만일",
  "year": 1995,
  "capo": 1,
  "measure": 4,
  "date": "2022-06-01",
  "score": [
    {
      "type": "v1",
      "contents": [
        {
          "chord": [{"name": "C"}, {"name": "G"}], 
          "nodelist": [
            {"grow": 1, "node": [null, null, null, null, 3, null]},
            {"grow": 1, "node": [null, null, 0, null, null, null]},
            {"grow": 1, "node": [null, 1, null, null, null, null]},
            {"grow": 1, "node": [null, 3, null, null, null, null]},
            {"grow": 1, "node": [0, null, null, null, null, 3]},
            {"grow": 1, "node": [null, 3, null, null, null, null]},
            {"grow": 1, "node": [null, 1, null, null, null, null]},
            {"grow": 1, "node": [null, 0, null, null, null, null]}
          ],
          "lyrics": []
        },
        {
          "chord": [{"name": "Am"}, {"name": "G/B"}], 
          "nodelist": [
            {"grow": 1, "node": [null, null, 2, null, 0, null]},
            {"grow": 1, "node": [null, 0, null, null, null, null]},
            {"grow": 1, "node": [null, 1, null, null, null, null]},
            {"grow": 1, "node": [null, 3, null, null, null, null]},
            {"grow": 1, "node": [null, 0, null, null, 2, null]},
            {"grow": 1, "node": [null, null, 0, null, null, null]},
            {"grow": 1, "node": [null, null, null, 0, null, null]},
            {"grow": 1, "node": [null, null, 0, null, null, null]}
          ],
          "lyrics": []
        },
        {
          "chord": [{"name": "C"}, {"name": "G"}], 
          "nodelist": [
            {"grow": 1, "node": [null, null, null, null, 3, null]},
            {"grow": 1, "node": [null, null, 0, null, null, null]},
            {"grow": 1, "node": [null, 1, null, null, null, null]},
            {"grow": 1, "node": [null, 3, null, null, null, null]},
            {"grow": 1, "node": [0, null, null, null, null, 3]},
            {"grow": 1, "node": [null, 3, null, null, null, null]},
            {"grow": 1, "node": [null, 1, null, null, null, null]},
            {"grow": 1, "node": [null, 0, null, null, null, null]}
          ],
          "lyrics": []
        },
        {
          "chord": [{"name": "Csus4", "grow": 1.7}, {"name": "C"}],
          "nodelist": [
            {"grow": 1, "node": [null, 1, null, null, 3, null]},
            {"grow": 1, "node": [null, null, 0, null, null, null]},
            {"grow": 1, "node": [1, null, null, null, null, null]},
            {"grow": 0.5, "node": [null, null, 0, null, null, null]},
            {"grow": 0.4, "node": [3, null, null, null, null, null]},
            {"grow": 0.4, "node": [1, null, null, null, null, null]},
            {"grow": 1.7, "node": [0, null, null, null, null, null]}
          ],
          "lyrics": []
        },
        {
          "chord": [{"name": "C"}, {"name": "G"}], 
          "lyrics": [
            {"text": "내가 만일"},
            {"text": "하늘이라"}
          ]
        },
        {
          "chord": [{"name": "C"}], 
          "lyrics": [
            {"text": "면"}
          ]
        },
        {
          "chord": [{"name": "C"}, {"name": "G"}], 
          "lyrics": [
            {"text": "그대 얼굴에"},
            {"text": "물들고 싶"}
          ]
        },
        {
          "chord": [{"name": "Am"}], 
          "lyrics": [
            {"text": "어-"}
          ]
        },
        {
          "chord": [{"name": "F"}, {"name": "C"}], 
          "lyrics": [
            {"text": "붉게 물든"},
            {"text": "저녁"}
          ]
        },
        {
          "chord": [{"name": "D"}, {"name": "G"}], 
          "lyrics": [
            {"text": "저 노을처"},
            {"text": "럼"},
            {"text": "나", "grow": 0}
          ]
        },
        {
          "chord": [{"name": "C"}, {"name": "G"}], 
          "lyrics": [
            {"text": "그대 뺨에"},
            {"text": "물들고 싶"}
          ]
        },
        {
          "chord": [{"name": "C"}], 
          "lyrics": [
            {"text": "어-"}
          ]
        },
        {
          "chord": [{"name": "C"}, {"name": "G"}], 
          "lyrics": [
            {"text": "내가 만일"},
            {"text": "시인이라"}
          ]
        },
        {
          "chord": [{"name": "C"}], 
          "lyrics": [
            {"text": "면"}
          ]
        },
        {
          "chord": [{"name": "C"}, {"name": "G"}], 
          "lyrics": [
            {"text": "그대 위해"},
            {"text": "노래하겠"}
          ]
        },
        {
          "chord": [{"name": "Am"}], 
          "lyrics": [
            {"text": "어-"}
          ]
        },
        {
          "chord": [{"name": "F"}, {"name": "C"}], 
          "lyrics": [
            {"text": "엄마 품에"},
            {"text": "안긴"},
            {"text": "어", "grow": 0}
          ]
        },
        {
          "chord": [{"name": "G"}, {"name": "Am x 2"}], 
          "lyrics": [
            {"text": "린 아이 처"},
            {"text": "럼"},
            {"text": "나", "grow": 0}
          ]
        },
        {
          "chord": [{"name": "C"}, {"name": "G"}], 
          "lyrics": [
            {"text": "행복하게 노"},
            {"text": "래하고 싶"}
          ]
        },
        {
          "chord": [{"name": "C"}], 
          "lyrics": [
            {"text": "어 -"}
          ]
        },
        {
          "chord": [{"name": "C"}, {"name": "F"}], 
          "lyrics": [
            {"text": "세상에"},
            {"text": "그", "grow": 0}
          ]
        },
        {
          "chord": [{"name": "G"}, {"name": "Am"}], 
          "lyrics": [
            {"text": "무엇이라"},
            {"text": "도"}
          ]
        },
        {
          "chord": [{"name": "C"}, {"name": "F"}], 
          "lyrics": [
            {"text": "그대 위해"},
            {"text": "되고 싶"}
          ]
        },
        {
          "chord": [{"name": "G"}], 
          "lyrics": [
            {"text": "어-"},
            {"text": "오", "grow": 0}
          ]
        },
        {
          "chord": [{"name": "C"}, {"name": "F"}], 
          "lyrics": [
            {"text": "늘 처럼"},
            {"text": "우리", "grow": 0}
          ]
        },
        {
          "chord": [{"name": "G"}, {"name": "Am"}], 
          "lyrics": [
            {"text": "함께 있음"},
            {"text": "이"},
            {"text": "내겐", "grow": 0}
          ]
        },
        {
          "chord": [{"name": "F"}, {"name": "C"}], 
          "lyrics": [
            {"text": "얼마나 큰"},
            {"text": "기쁨인"}
          ]
        },
        {
          "chord": [{"name": "G"}], 
          "lyrics": [
            {"text": "지-"},
            {"text": "사랑", "grow": 0}
          ]
        },
        {
          "chord": [{"name": "C"}, {"name": "F"}], 
          "lyrics": [
            {"text": "하는 나의"},
            {"text": "사람아"}
          ]
        },
        {
          "chord": [{"name": "G"}, {"name": "Am"}], 
          "lyrics": [
            {"text": "너는 아니"},
            {"text": "워 -", "grow": 0}
          ]
        },
        {
          "chord": [{"name": "F"}, {"name": "G"}], 
          "lyrics": [
            {"text": "어 - 이런"},
            {"text": "나의 마"}
          ]
        },
        {
          "chord": [{"name": "C"}], 
          "lyrics": [
            {"text": "음을-"}
          ]
        },
        {
          "chord": [{"name": "C"}, {"name": "G"}], 
          "nodelist": [
            {"grow": 1, "node": [null, null, null, null, 3, null]},
            {"grow": 1, "node": [null, null, 0, null, null, null]},
            {"grow": 1, "node": [null, 1, null, null, null, null]},
            {"grow": 1, "node": [null, 3, null, null, null, null]},
            {"grow": 1, "node": [0, null, null, null, null, 3]},
            {"grow": 1, "node": [null, 3, null, null, null, null]},
            {"grow": 1, "node": [null, 1, null, null, null, null]},
            {"grow": 1, "node": [null, 0, null, null, null, null]}
          ],
          "lyrics": []
        },
        {
          "chord": [{"name": "Am"}, {"name": "G/B"}], 
          "nodelist": [
            {"grow": 1, "node": [null, null, 2, null, 0, null]},
            {"grow": 1, "node": [null, 0, null, null, null, null]},
            {"grow": 1, "node": [null, 1, null, null, null, null]},
            {"grow": 1, "node": [null, 3, null, null, null, null]},
            {"grow": 1, "node": [null, 0, null, null, 2, null]},
            {"grow": 1, "node": [null, null, 0, null, null, null]},
            {"grow": 1, "node": [null, null, null, 0, null, null]},
            {"grow": 1, "node": [null, null, 0, null, null, null]}
          ],
          "lyrics": []
        },
        {
          "chord": [{"name": "C"}, {"name": "G"}], 
          "nodelist": [
            {"grow": 1, "node": [null, null, null, null, 3, null]},
            {"grow": 1, "node": [null, null, 0, null, null, null]},
            {"grow": 1, "node": [null, 1, null, null, null, null]},
            {"grow": 1, "node": [null, 3, null, null, null, null]},
            {"grow": 1, "node": [0, null, null, null, null, 3]},
            {"grow": 1, "node": [null, 3, null, null, null, null]},
            {"grow": 1, "node": [null, 1, null, null, null, null]},
            {"grow": 1, "node": [null, 0, null, null, null, null]}
          ],
          "lyrics": []
        },
        {
          "chord": [{"name": "Csus4", "grow": 1.7}, {"name": "C"}],
          "nodelist": [
            {"grow": 1, "node": [null, 1, null, null, 3, null]},
            {"grow": 1, "node": [null, null, 0, null, null, null]},
            {"grow": 1, "node": [1, null, null, null, null, null]},
            {"grow": 0.5, "node": [null, null, 0, null, null, null]},
            {"grow": 0.4, "node": [3, null, null, null, null, null]},
            {"grow": 0.4, "node": [1, null, null, null, null, null]},
            {"grow": 1.7, "node": [0, null, null, null, null, null]}
          ],
          "lyrics": []
        },
        {
          "chord": [{"name": "C"}, {"name": "G"}], 
          "lyrics": [
            {"text": "내가 만일"},
            {"text": "구름이라"}
          ]
        },
        {
          "chord": [{"name": "C"}], 
          "lyrics": [
            {"text": "면"}
          ]
        },
        {
          "chord": [{"name": "C"}, {"name": "G"}], 
          "lyrics": [
            {"text": "그대 위해"},
            {"text": "비가 되겠"}
          ]
        },
        {
          "chord": [{"name": "Am"}], 
          "lyrics": [
            {"text": "어 -"}
          ]
        },
        {
          "chord": [{"name": "F"}, {"name": "C"}], 
          "lyrics": [
            {"text": "더운 여름"},
            {"text": "날의"}
          ]
        },
        {
          "chord": [{"name": "G"}, {"name": "Am"}], 
          "lyrics": [
            {"text": "소나기"},
            {"text": "처럼"},
            {"text": "나", "grow": 0}
          ]
        },
        {
          "chord": [{"name": "C"}, {"name": "G"}], 
          "lyrics": [
            {"text": "시원하게"},
            {"text": "내리고 싶"}
          ]
        },
        {
          "chord": [{"name": "C"}], 
          "lyrics": [
            {"text": "어 -"}
          ]
        },
        {
          "chord": [{"name": "C"}, {"name": "F"}], 
          "lyrics": [
            {"text": "세상에"},
            {"text": "그", "grow": 0}
          ]
        },
        {
          "chord": [{"name": "G"}, {"name": "Am"}], 
          "lyrics": [
            {"text": "무엇이라"},
            {"text": "도"}
          ]
        },
        {
          "chord": [{"name": "C"}, {"name": "F"}], 
          "lyrics": [
            {"text": "그대 위해"},
            {"text": "되고 싶"}
          ]
        },
        {
          "chord": [{"name": "G"}], 
          "lyrics": [
            {"text": "어-"},
            {"text": "오", "grow": 0}
          ]
        },
        {
          "chord": [{"name": "C"}, {"name": "F"}], 
          "lyrics": [
            {"text": "늘 처럼"},
            {"text": "우리", "grow": 0}
          ]
        },
        {
          "chord": [{"name": "G"}, {"name": "Am"}], 
          "lyrics": [
            {"text": "함께 있음"},
            {"text": "이"},
            {"text": "내겐", "grow": 0}
          ]
        },
        {
          "chord": [{"name": "F"}, {"name": "C"}], 
          "lyrics": [
            {"text": "얼마나 큰"},
            {"text": "기쁨인"}
          ]
        },
        {
          "chord": [{"name": "G"}], 
          "lyrics": [
            {"text": "지-"},
            {"text": "사랑", "grow": 0}
          ]
        },
        {
          "chord": [{"name": "C"}, {"name": "F"}], 
          "lyrics": [
            {"text": "하는 나의"},
            {"text": "사람아"}
          ]
        },
        {
          "chord": [{"name": "G"}, {"name": "Am"}], 
          "lyrics": [
            {"text": "너는 아니"},
            {"text": "워 -", "grow": 0}
          ]
        },
        {
          "chord": [{"name": "F"}, {"name": "G"}], 
          "lyrics": [
            {"text": "어 - 이런"},
            {"text": "나의 마"}
          ]
        },
        {
          "chord": [{"name": "C"}], 
          "lyrics": [
            {"text": "음을-"}
          ]
        },
        {
          "chord": [{"name": "C"}, {"name": "G"}], 
          "nodelist": [
            {"grow": 1, "node": [null, null, null, null, 3, null]},
            {"grow": 1, "node": [null, null, 0, null, null, null]},
            {"grow": 1, "node": [null, 1, null, null, null, null]},
            {"grow": 1, "node": [null, 3, null, null, null, null]},
            {"grow": 1, "node": [0, null, null, null, null, 3]},
            {"grow": 1, "node": [null, 3, null, null, null, null]},
            {"grow": 1, "node": [null, 1, null, null, null, null]},
            {"grow": 1, "node": [null, 0, null, null, null, null]}
          ],
          "lyrics": []
        },
        {
          "chord": [{"name": "Am"}, {"name": "G/B"}], 
          "nodelist": [
            {"grow": 1, "node": [null, null, 2, null, 0, null]},
            {"grow": 1, "node": [null, 0, null, null, null, null]},
            {"grow": 1, "node": [null, 1, null, null, null, null]},
            {"grow": 1, "node": [null, 3, null, null, null, null]},
            {"grow": 1, "node": [null, 0, null, null, 2, null]},
            {"grow": 1, "node": [null, null, 0, null, null, null]},
            {"grow": 1, "node": [null, null, null, 0, null, null]},
            {"grow": 1, "node": [null, null, 0, null, null, null]}
          ],
          "lyrics": []
        },
        {
          "chord": [{"name": "C"}, {"name": "G"}], 
          "nodelist": [
            {"grow": 1, "node": [null, null, null, null, 3, null]},
            {"grow": 1, "node": [null, null, 0, null, null, null]},
            {"grow": 1, "node": [null, 1, null, null, null, null]},
            {"grow": 1, "node": [null, 3, null, null, null, null]},
            {"grow": 1, "node": [0, null, null, null, null, 3]},
            {"grow": 1, "node": [null, 3, null, null, null, null]},
            {"grow": 1, "node": [null, 1, null, null, null, null]},
            {"grow": 1, "node": [null, 0, null, null, null, null]}
          ],
          "lyrics": []
        },
        {
          "chord": [{"name": "Csus4", "grow": 1.9}, {"name": "C"}],
          "nodelist": [
            {"grow": 1, "node": [null, null, null, null, 3, null]},
            {"grow": 1, "node": [null, null, 0, null, null, null]},
            {"grow": 1, "node": [1, 1, null, null, null, null]},
            {"grow": 1, "node": [null, null, 0, null, null, null]},
            {"grow": 2, "node": [0, 1, 0, 2, 3, null]}
          ],
          "lyrics": []
        }
      ]
    }
  ]
}